shinc/__init__.py
shinc/ocr/__init__.py
shinc/ocr/sofextractor.py
shinc/sof/__init__.py
shinc/sof/sof.py
shinc_lib_sofs-7.0.0.dist-info/METADATA
shinc_lib_sofs-7.0.0.dist-info/WHEEL
shinc_lib_sofs-7.0.0.dist-info/top_level.txt
shinc_lib_sofs-7.0.0.dist-info/RECORD
