Metadata-Version: 2.1
Name: shinc-lib-sofs
Version: 7.0.0
Summary: SOF interpreter
Home-page: UNKNOWN
Author: William Greenly
Author-email: william_greenly@hotmail.com
License: UNKNOWN
Platform: UNKNOWN
Classifier: Programming Language :: Python :: 3
Classifier: License :: OSI Approved :: MIT License
Classifier: Operating System :: OS Independent
Requires-Python: >=3.6
Requires-Dist: pytesseract
Requires-Dist: twine
Requires-Dist: Pillow
Requires-Dist: PyPDF2
Requires-Dist: rdflib
Requires-Dist: pdfplumber
Requires-Dist: python-dateutil
Requires-Dist: dateparser
